fairmofsyncondition/__init__.py
fairmofsyncondition/call_model/__init__.py
fairmofsyncondition/call_model/run_model.py
fairmofsyncondition/call_model/trained_models/target_scaler_energy.pkl
fairmofsyncondition/call_model/utils_model.py
fairmofsyncondition/cluster/__init__.py
fairmofsyncondition/cluster/cluster_data/clusters_clusters.png
fairmofsyncondition/cluster/clustering.py
fairmofsyncondition/cluster/number_of_clusters.png
fairmofsyncondition/crystal/__init__.py
fairmofsyncondition/crystal/analysis.py
fairmofsyncondition/crystal/crystal2data.py
fairmofsyncondition/db/category_names.msgpack
fairmofsyncondition/db/iupacname_smiles.msgpack
fairmofsyncondition/db/ligands_to_solvents.json
fairmofsyncondition/db/metal_salts_to_solvents.json
fairmofsyncondition/db/solvent_to_inchi_and_smile.json
fairmofsyncondition/featurizer/__init__.py
fairmofsyncondition/featurizer/encoder.py
fairmofsyncondition/geometry/__init__.py
fairmofsyncondition/geometry/analysis.py
fairmofsyncondition/geometry/grapher.py
fairmofsyncondition/model/__init__.py
fairmofsyncondition/model/hyper_optimiser.py
fairmofsyncondition/model/thermodynamic_stability.py
fairmofsyncondition/read_write/__init__.py
fairmofsyncondition/read_write/cheminfo2iupac.py
fairmofsyncondition/read_write/coords_library.py
fairmofsyncondition/read_write/filetyper.py
fairmofsyncondition/read_write/iupacname2cheminfo.py
fairmofsyncondition/read_write/struct2iupac.py
fairmofsyncondition-0.1.4.dist-info/LICENSE
fairmofsyncondition-0.1.4.dist-info/METADATA
fairmofsyncondition-0.1.4.dist-info/WHEEL
fairmofsyncondition-0.1.4.dist-info/entry_points.txt
fairmofsyncondition-0.1.4.dist-info/RECORD
