Metadata-Version: 2.1
Name: fairmofsyncondition
Version: 0.1.4
Summary: A python machine learning module for for accelerating the discovery and synthesis of Metal organic frameworks
Author: Dinga Wonanke
Author-email: bafgreat@gmail.com
Requires-Python: >=3.10,<4.0
Classifier: Programming Language :: Python :: 3
Classifier: Programming Language :: Python :: 3.10
Classifier: Programming Language :: Python :: 3.11
Classifier: Programming Language :: Python :: 3.12
Requires-Dist: ase (>=3.23.0)
Requires-Dist: attr (>=0.3.2,<0.4.0)
Requires-Dist: lmdb (>=1.5.1,<2.0.0)
Requires-Dist: lmfit (>=1.3.2,<2.0.0)
Requires-Dist: mofstructure (>=0.1.8.4)
Requires-Dist: msgpack (>=1.1.0,<2.0.0)
Requires-Dist: notebook (>=7.3.1,<8.0.0)
Requires-Dist: numpy (<2) ; sys_platform == "darwin"
Requires-Dist: numpy ; sys_platform == "linux"
Requires-Dist: numpy ; sys_platform == "win32"
Requires-Dist: optuna (>=4.1.0,<5.0.0)
Requires-Dist: optuna-dashboard (>=0.17.0,<0.18.0)
Requires-Dist: pandas (>=2.2.2,<3.0.0)
Requires-Dist: pubchempy (>=1.0.5,<2.0.0)
Requires-Dist: pytest (>=8.3.2,<9.0.0)
Requires-Dist: pytorch-lightning (>=2.4.0)
Requires-Dist: scikit-learn (>=1.7.1)
Requires-Dist: sentence-transformers (>=3.4.1,<4.0.0)
Requires-Dist: six (>=1.16.0,<2.0.0)
Requires-Dist: tensorboard (>=2.18.0,<3.0.0)
Requires-Dist: torch (==2.2.2) ; sys_platform == "darwin"
Requires-Dist: torch ; sys_platform == "linux"
Requires-Dist: torch ; sys_platform == "win32"
Requires-Dist: torch-geometric (>=2.6.1,<3.0.0)
Requires-Dist: tornado (>=6.4.2,<7.0.0)
Requires-Dist: transformers (>=4.45.1,<5.0.0)
